setup_server.py
message_server_learning_proj.egg-info/PKG-INFO
message_server_learning_proj.egg-info/SOURCES.txt
message_server_learning_proj.egg-info/dependency_links.txt
message_server_learning_proj.egg-info/requires.txt
message_server_learning_proj.egg-info/top_level.txt
serv/__init__.py
serv/server.py
serv/common/__init__.py
serv/common/decos.py
serv/common/discripts.py
serv/common/errors.py
serv/common/metaclasses.py
serv/common/utils.py
serv/common/variables.py
serv/doc/__init__.py
serv/doc/source/__init__.py
serv/doc/source/conf.py
serv/log/__init__.py
serv/log/config_client.py
serv/log/config_server.py
serv/server/__init__.py
serv/server/core.py
serv/server/server_db.py
serv/server/server_gui.py
serv/unit_tests/__init__.py
serv/unit_tests/test_client.py
serv/unit_tests/test_server.py
serv/unit_tests/test_utils.py